[
    {
        "type": "sound_effect",
        "id" : "fire_gun",
        "volume" : 75,
        "variant" : "bond_410",
        "files" : [
            "guns/45/45_1.ogg",
			"guns/45/45_2.ogg",
			"guns/45/45_3.ogg",
			"guns/45/45_4.ogg",
			"guns/45/45_5.ogg",
			"guns/45/45_6.ogg",
			"guns/45/45_7.ogg",
			"guns/45/45_8.ogg"
        ]
    },
	{
        "type": "sound_effect",
        "id" : "fire_gun_distant",
        "volume" : 60,
        "variant" : "bond_410",
        "files" : [
            "guns/45/45_1.ogg",
			"guns/45/45_2.ogg",
			"guns/45/45_3.ogg",
			"guns/45/45_4.ogg",
			"guns/45/45_5.ogg",
			"guns/45/45_6.ogg",
			"guns/45/45_7.ogg",
			"guns/45/45_8.ogg"
        ]
    },
    {
        "type": "sound_effect",
        "id" : "reload",
        "volume" : 75,
        "variant" : "bond_410",
        "files" : [
            "guns/reload/revolver/revolver_1.ogg",
			"guns/reload/revolver/revolver_2.ogg",
			"guns/reload/revolver/revolver_3.ogg",
			"guns/reload/revolver/revolver_4.ogg",
			"guns/reload/revolver/revolver_5.ogg"
        ]
    },
    {
        "type": "sound_effect",
        "id" : "fire_gun",
        "volume" : 75,
        "variant" : "colt_lightning",
        "files" : [
            "guns/45/45_1.ogg",
			"guns/45/45_2.ogg",
			"guns/45/45_3.ogg",
			"guns/45/45_4.ogg",
			"guns/45/45_5.ogg",
			"guns/45/45_6.ogg",
			"guns/45/45_7.ogg",
			"guns/45/45_8.ogg"
        ]
    },
	{
        "type": "sound_effect",
        "id" : "fire_gun_distant",
        "volume" : 60,
        "variant" : "colt_lightning",
        "files" : [
            "guns/45/45_1.ogg",
			"guns/45/45_2.ogg",
			"guns/45/45_3.ogg",
			"guns/45/45_4.ogg",
			"guns/45/45_5.ogg",
			"guns/45/45_6.ogg",
			"guns/45/45_7.ogg",
			"guns/45/45_8.ogg"
        ]
    },
    {
        "type": "sound_effect",
        "id" : "reload",
        "volume" : 75,
        "variant" : "colt_lightning",
        "files" : [
            "guns/reload/rifle_s/rifle_1.ogg",
			"guns/reload/rifle_s/rifle_2.ogg",
			"guns/reload/rifle_s/rifle_3.ogg",
			"guns/reload/rifle_s/rifle_4.ogg",
			"guns/reload/rifle_s/rifle_5.ogg"
        ]
    },
    {
        "type": "sound_effect",
        "id" : "fire_gun",
        "volume" : 75,
        "variant" : "colt_saa",
        "files" : [
            "guns/45/45_1.ogg",
			"guns/45/45_2.ogg",
			"guns/45/45_3.ogg",
			"guns/45/45_4.ogg",
			"guns/45/45_5.ogg",
			"guns/45/45_6.ogg",
			"guns/45/45_7.ogg",
			"guns/45/45_8.ogg"
        ]
    },
	{
        "type": "sound_effect",
        "id" : "fire_gun_distant",
        "volume" : 60,
        "variant" : "colt_saa",
        "files" : [
            "guns/45/45_1.ogg",
			"guns/45/45_2.ogg",
			"guns/45/45_3.ogg",
			"guns/45/45_4.ogg",
			"guns/45/45_5.ogg",
			"guns/45/45_6.ogg",
			"guns/45/45_7.ogg",
			"guns/45/45_8.ogg"
        ]
    },
    {
        "type": "sound_effect",
        "id" : "reload",
        "volume" : 75,
        "variant" : "colt_saa",
        "files" : [
            "guns/reload/revolver/revolver_1.ogg",
			"guns/reload/revolver/revolver_2.ogg",
			"guns/reload/revolver/revolver_3.ogg",
			"guns/reload/revolver/revolver_4.ogg",
			"guns/reload/revolver/revolver_5.ogg"
        ]
    }
]
